FASTRAL/Sampler.py
FASTRAL/__init__.py
FASTRAL/fastral.py
FASTRAL/fastral_infer.py
FASTRAL/utils.py
FASTRAL/ASTRAL-modified/LICENSE
FASTRAL/ASTRAL-modified/README.md
FASTRAL/ASTRAL-modified/__init__.py
FASTRAL/ASTRAL-modified/make.sh
FASTRAL/ASTRAL-modified/manifest.text
FASTRAL/ASTRAL-modified/.github/ISSUE_TEMPLATE/bug_report.md
FASTRAL/ASTRAL-modified/.github/ISSUE_TEMPLATE/feature_request.md
FASTRAL/ASTRAL-modified/lib/JSAP-2.1.jar
FASTRAL/ASTRAL-modified/lib/colt.jar
FASTRAL/ASTRAL-modified/lib/main.jar
FASTRAL/ASTRAL-modified/main/phylonet/coalescent/AbstractClusterCollection$1$1.class
FASTRAL/ASTRAL-modified/main/phylonet/coalescent/AbstractClusterCollection$1.class
FASTRAL/ASTRAL-modified/main/phylonet/coalescent/AbstractClusterCollection.class
FASTRAL/ASTRAL-modified/main/phylonet/coalescent/AbstractClusterCollection.java
FASTRAL/ASTRAL-modified/main/phylonet/coalescent/AbstractComputeMinCostTask.class
FASTRAL/ASTRAL-modified/main/phylonet/coalescent/AbstractComputeMinCostTask.java
FASTRAL/ASTRAL-modified/main/phylonet/coalescent/AbstractDataCollection.class
FASTRAL/ASTRAL-modified/main/phylonet/coalescent/AbstractDataCollection.java
FASTRAL/ASTRAL-modified/main/phylonet/coalescent/AbstractInference.class
FASTRAL/ASTRAL-modified/main/phylonet/coalescent/AbstractInference.java
FASTRAL/ASTRAL-modified/main/phylonet/coalescent/AbstractPartition.class
FASTRAL/ASTRAL-modified/main/phylonet/coalescent/AbstractPartition.java
FASTRAL/ASTRAL-modified/main/phylonet/coalescent/AbstractWeightCalculator.class
FASTRAL/ASTRAL-modified/main/phylonet/coalescent/AbstractWeightCalculator.java
FASTRAL/ASTRAL-modified/main/phylonet/coalescent/BipartitionWeightCalculator$Intersects.class
FASTRAL/ASTRAL-modified/main/phylonet/coalescent/BipartitionWeightCalculator$Quadrapartition.class
FASTRAL/ASTRAL-modified/main/phylonet/coalescent/BipartitionWeightCalculator$Results.class
FASTRAL/ASTRAL-modified/main/phylonet/coalescent/BipartitionWeightCalculator.class
FASTRAL-1.0.0.dist-info/LICENSE
FASTRAL-1.0.0.dist-info/METADATA
FASTRAL-1.0.0.dist-info/WHEEL
FASTRAL-1.0.0.dist-info/entry_points.txt
FASTRAL-1.0.0.dist-info/top_level.txt
FASTRAL-1.0.0.dist-info/RECORD
