Metadata-Version: 2.1
Name: FASTRAL
Version: 1.0.0
Summary: A hybrid summary method for reconstructing species tree from gene trees.
Home-page: https://github.com/PayamDiba/FASTRAL
Author: Payam Dibaeinia
Author-email: dibaein2@illinois.edu
License: MIT License
Platform: UNKNOWN
Classifier: Programming Language :: Python :: 3
Classifier: License :: OSI Approved :: MIT License
Requires-Python: >3.5.2
Requires-Dist: numpy
Requires-Dist: pandas
Requires-Dist: absl-py
